odoo/addons/ssi_helpdesk_data_requirement/README.rst
odoo/addons/ssi_helpdesk_data_requirement/__init__.py
odoo/addons/ssi_helpdesk_data_requirement/__manifest__.py
odoo/addons/ssi_helpdesk_data_requirement/models/__init__.py
odoo/addons/ssi_helpdesk_data_requirement/models/helpdesk_ticket.py
odoo/addons/ssi_helpdesk_data_requirement/models/helpdesk_type.py
odoo/addons/ssi_helpdesk_data_requirement/security/ir.model.access.csv
odoo/addons/ssi_helpdesk_data_requirement/static/description/icon.png
odoo/addons/ssi_helpdesk_data_requirement/views/helpdesk_type_views.xml
odoo14_addon_ssi_helpdesk_data_requirement-14.0.1.1.0.dist-info/METADATA
odoo14_addon_ssi_helpdesk_data_requirement-14.0.1.1.0.dist-info/WHEEL
odoo14_addon_ssi_helpdesk_data_requirement-14.0.1.1.0.dist-info/top_level.txt
odoo14_addon_ssi_helpdesk_data_requirement-14.0.1.1.0.dist-info/RECORD
